CHANGES.txt
LICENSE.txt
MANIFEST.in
README.md
setup.py
crecaptcha.egg-info/PKG-INFO
crecaptcha.egg-info/SOURCES.txt
crecaptcha.egg-info/dependency_links.txt
crecaptcha.egg-info/top_level.txt
crecatpcha/__init__.py
crecatpcha/crecaptcha.py
crecatpcha/django_crecatpcha.py
docs/usage.txt