Metadata-Version: 2.1
Name: crecaptcha
Version: 0.1.32
Summary: reCatpcha api v3.0 - with django support
Home-page: https://github.com/cristiansteib/crecaptcha/
Author: Steib Cristian
Author-email: cristiansteib@gmail.com
License: LICENSE.txt
Platform: UNKNOWN
Classifier: Programming Language :: Python :: 3
Classifier: Operating System :: OS Independent
Classifier: Framework :: Django
Classifier: Framework :: Flask
Classifier: License :: OSI Approved :: Apache Software License
Classifier: Topic :: Security
Classifier: Development Status :: 5 - Production/Stable
